openmnglab/__init__.py
openmnglab/datamodel/__init__.py
openmnglab/datamodel/exceptions.py
openmnglab/datamodel/matplot/__init__.py
openmnglab/datamodel/matplot/model.py
openmnglab/datamodel/pandas/__init__.py
openmnglab/datamodel/pandas/model.py
openmnglab/datamodel/pandas/schemas.py
openmnglab/datamodel/pandas/verification.py
openmnglab/execution/__init__.py
openmnglab/execution/exceptions.py
openmnglab/execution/singlethreaded.py
openmnglab/functions/__init__.py
openmnglab/functions/analysis/__init__.py
openmnglab/functions/analysis/funcs/__init__.py
openmnglab/functions/analysis/funcs/spdf_components.py
openmnglab/functions/analysis/funcs/spdf_features.py
openmnglab/functions/analysis/spdf_components.py
openmnglab/functions/analysis/spdf_features.py
openmnglab/functions/base.py
openmnglab/functions/helpers/__init__.py
openmnglab/functions/helpers/general.py
openmnglab/functions/helpers/quantity_helpers.py
openmnglab/functions/input/__init__.py
openmnglab/functions/input/readers/__init__.py
openmnglab/functions/input/readers/dapsys_reader.py
openmnglab/functions/input/readers/funcs/__init__.py
openmnglab/functions/input/readers/funcs/dapsys_reader.py
openmnglab/functions/input/readers/funcs/spike2/__init__.py
openmnglab/functions/input/readers/funcs/spike2/hdfmat.py
openmnglab/functions/input/readers/funcs/spike2/structs.py
openmnglab/functions/input/readers/funcs/spike2_reader.py
openmnglab/functions/input/readers/spike2_reader.py
openmnglab/functions/plot/__init__.py
openmnglab/functions/plot/funcs/__init__.py
openmnglab/functions/plot/funcs/continuous.py
openmnglab/functions/plot/funcs/waveforms.py
openmnglab/functions/plot/waveforms.py
openmnglab/functions/processing/__init__.py
openmnglab/functions/processing/funcs/__init__.py
openmnglab/functions/processing/funcs/static_intervals.py
openmnglab/functions/processing/funcs/windows.py
openmnglab/functions/processing/static_intervals.py
openmnglab/functions/processing/windows.py
openmnglab/model/__init__.py
openmnglab-0.3.0.dist-info/LICENSE
openmnglab-0.3.0.dist-info/METADATA
openmnglab-0.3.0.dist-info/WHEEL
openmnglab-0.3.0.dist-info/RECORD
