Metadata-Version: 2.1
Name: openmnglab
Version: 0.3.0
Summary: A Python framework for microneurography analysis
Home-page: https://github.com/Digital-C-Fiber/openMNGlab
License: MIT
Keywords: microneurography,neurophysiology,electrophysiology
Author: Peter Konradi
Author-email: codingchipmunk@posteo.net
Requires-Python: >=3.11,<4.0
Classifier: Development Status :: 3 - Alpha
Classifier: Intended Audience :: Developers
Classifier: Intended Audience :: Healthcare Industry
Classifier: Intended Audience :: Science/Research
Classifier: License :: OSI Approved :: MIT License
Classifier: Programming Language :: Python :: 3
Classifier: Programming Language :: Python :: 3.11
Classifier: Programming Language :: Python :: 3 :: Only
Requires-Dist: h5py (>=3.9.0,<4.0.0)
Requires-Dist: matplotlib (>=3.7.1,<4.0.0)
Requires-Dist: pandas (>=2.0.1,<3.0.0)
Requires-Dist: pandera (>=0.14.5,<0.15.0)
Requires-Dist: quantities (>=0.14.1,<0.15.0)
Requires-Dist: seaborn (>=0.12.2,<0.13.0)
Project-URL: Documentation, https://openmnglab.readthedocs.io/en/latest/
Project-URL: Repository, https://github.com/Digital-C-Fiber/openMNGlab
